odoo/addons/fastapi/README.rst
odoo/addons/fastapi/__init__.py
odoo/addons/fastapi/__manifest__.py
odoo/addons/fastapi/context.py
odoo/addons/fastapi/dependencies.py
odoo/addons/fastapi/depends.py
odoo/addons/fastapi/error_handlers.py
odoo/addons/fastapi/fastapi_dispatcher.py
odoo/addons/fastapi/http.py
odoo/addons/fastapi/schemas.py
odoo/addons/fastapi/demo/fastapi_endpoint_demo.xml
odoo/addons/fastapi/i18n/fastapi.pot
odoo/addons/fastapi/models/__init__.py
odoo/addons/fastapi/models/fastapi_endpoint.py
odoo/addons/fastapi/models/fastapi_endpoint_demo.py
odoo/addons/fastapi/models/ir_rule.py
odoo/addons/fastapi/models/res_lang.py
odoo/addons/fastapi/readme/CONTRIBUTORS.rst
odoo/addons/fastapi/readme/DESCRIPTION.rst
odoo/addons/fastapi/readme/ROADMAP.rst
odoo/addons/fastapi/readme/USAGE.rst
odoo/addons/fastapi/routers/__init__.py
odoo/addons/fastapi/routers/demo_router.py
odoo/addons/fastapi/security/fastapi_endpoint.xml
odoo/addons/fastapi/security/ir_rule+acl.xml
odoo/addons/fastapi/security/res_groups.xml
odoo/addons/fastapi/static/description/endpoint_create.png
odoo/addons/fastapi/static/description/icon.png
odoo/addons/fastapi/static/description/index.html
odoo/addons/fastapi/tests/__init__.py
odoo/addons/fastapi/tests/common.py
odoo/addons/fastapi/tests/test_fastapi.py
odoo/addons/fastapi/tests/test_fastapi_demo.py
odoo/addons/fastapi/views/fastapi_endpoint.xml
odoo/addons/fastapi/views/fastapi_endpoint_demo.xml
odoo/addons/fastapi/views/fastapi_menu.xml
odoo14_addon_fastapi-14.0.1.0.0.dist-info/METADATA
odoo14_addon_fastapi-14.0.1.0.0.dist-info/WHEEL
odoo14_addon_fastapi-14.0.1.0.0.dist-info/top_level.txt
odoo14_addon_fastapi-14.0.1.0.0.dist-info/RECORD
