Metadata-Version: 2.1
Name: odoo14-addon-fastapi
Version: 14.0.1.0.0
Summary: Odoo FastAPI endpoint
Home-page: https://github.com/OCA/rest-framework
Author: ACSONE SA/NV,Odoo Community Association (OCA)
Author-email: support@odoo-community.org
License: LGPL-3
Platform: UNKNOWN
Classifier: Programming Language :: Python
Classifier: Framework :: Odoo
Classifier: Framework :: Odoo :: 14.0
Classifier: License :: OSI Approved :: GNU Lesser General Public License v3 (LGPLv3)
Classifier: Development Status :: 4 - Beta
Requires-Python: >=3.8
Requires-Dist: a2wsgi
Requires-Dist: fastapi
Requires-Dist: odoo14-addon-base-contextvars
Requires-Dist: odoo14-addon-endpoint-route-handler
Requires-Dist: odoo <14.1dev,>=14.0a
Requires-Dist: parse-accept-language
Requires-Dist: pydantic <2
Requires-Dist: python-multipart
Requires-Dist: ujson
